tapescript/AMHL.py
tapescript/__init__.py
tapescript/classes.py
tapescript/errors.py
tapescript/functions.py
tapescript/interfaces.py
tapescript/notes.md
tapescript/parsing.py
tapescript/tools.py
tapescript/version.py
tapescript-0.7.2.dist-info/METADATA
tapescript-0.7.2.dist-info/WHEEL
tapescript-0.7.2.dist-info/entry_points.txt
tapescript-0.7.2.dist-info/RECORD
