Metadata-Version: 2.4
Name: tapescript
Version: 0.7.2
Summary: Bytecode VM for embedding ACL in distributed systems
Project-URL: Homepage, https://github.com/k98kurz/tapescript
Project-URL: Repository, https://github.com/k98kurz/tapescript
Project-URL: Bug Tracker, https://github.com/k98kurz/tapescript/issues
Author-email: k98kurz <k98kurz@gmail.com>
Classifier: Development Status :: 3 - Alpha
Classifier: License :: OSI Approved :: ISC License (ISCL)
Classifier: Operating System :: OS Independent
Classifier: Programming Language :: Other Scripting Engines
Classifier: Programming Language :: Python :: 3
Classifier: Topic :: Security :: Cryptography
Requires-Python: >=3.10
Requires-Dist: pynacl>=1.5.0
Provides-Extra: docs
Requires-Dist: autodox>=0.1.16; extra == 'docs'
